_librapid.cpython-39-darwin.so
librapid/librapid
librapid/__init__.py
librapid/cxxblas/LICENSE
librapid/cxxblas/README.md
librapid/cxxblas/netlib/Makefile
librapid/.dylibs/libomp.dylib
librapid/bindings/__init__.py
librapid/bindings/python/__init__.py
librapid/bindings/generators/shapeGenerator.py
librapid/bindings/generators/argument.py
librapid/bindings/generators/file.py
librapid/bindings/generators/module.py
librapid/bindings/generators/main.py
librapid/bindings/generators/function.py
librapid/bindings/generators/class_.py
librapid/bindings/generators/arrayGenerator.py
librapid/vendor/xsimd/readthedocs.yml
librapid/vendor/xsimd/xsimd.pc.in
librapid/vendor/xsimd/xsimdConfig.cmake.in
librapid/vendor/xsimd/LICENSE
librapid/vendor/xsimd/environment.yml
librapid/vendor/xsimd/README.md
librapid/vendor/xsimd/.gitignore
librapid/vendor/xsimd/install_sde.sh
librapid/vendor/xsimd/CONTRIBUTING.md
librapid/vendor/xsimd/.clang-format
librapid/vendor/xsimd/Changelog.rst
librapid/vendor/xsimd/.git
librapid/vendor/xsimd/test/avx2.sh
librapid/vendor/xsimd/test/check_inline_specifier.sh
librapid/vendor/xsimd/test/ssse3.sh
librapid/vendor/xsimd/test/sse4_1.sh
librapid/vendor/xsimd/test/sse4_2.sh
librapid/vendor/xsimd/test/avx.sh
librapid/vendor/xsimd/test/sse2.sh
librapid/vendor/xsimd/test/sse.sh
librapid/vendor/xsimd/test/sse3.sh
librapid/vendor/xsimd/test/test_wasm/test_wasm.sh
librapid/vendor/xsimd/test/test_wasm/test_wasm_playwright.py
librapid/vendor/xsimd/test/test_wasm/browser_main.html
librapid/vendor/xsimd/docs/environment.yml
librapid/vendor/xsimd/docs/Makefile
librapid/vendor/xsimd/docs/make.bat
librapid/vendor/xsimd/docs/Doxyfile
librapid/vendor/xsimd/docs/source/index.rst
librapid/vendor/xsimd/docs/source/basic_usage.rst
librapid/vendor/xsimd/docs/source/conf.py
librapid/vendor/xsimd/docs/source/conda.svg
librapid/vendor/xsimd/docs/source/xsimd.svg
librapid/vendor/xsimd/docs/source/vectorized_code.rst
librapid-0.7.5.dist-info/RECORD
librapid-0.7.5.dist-info/WHEEL
librapid-0.7.5.dist-info/entry_points.txt
librapid-0.7.5.dist-info/METADATA
librapid-0.7.5.dist-info/licenses/LICENSE
