Metadata-Version: 2.1
Name: librapid
Version: 0.7.5
Summary: A high-performance library for arrays and numeric calculations
Keywords: librapid high-performance computing c++ mathematics array matrix vector tensor gpu cuda openmp multithreading multicore parallel
Home-page: https://tobydavis.dev/librapid
License: MIT License
Classifier: Development Status :: 4 - Beta
Classifier: Intended Audience :: Developers
Classifier: Intended Audience :: Science/Research
Classifier: License :: OSI Approved :: MIT License
Classifier: Operating System :: MacOS
Classifier: Operating System :: Microsoft :: Windows
Classifier: Operating System :: POSIX :: Linux
Classifier: Programming Language :: C++
Classifier: Programming Language :: Python :: 3
Classifier: Programming Language :: Python :: 3.6
Classifier: Programming Language :: Python :: 3.7
Classifier: Programming Language :: Python :: 3.8
Classifier: Programming Language :: Python :: 3.9
Classifier: Programming Language :: Python :: 3.10
Classifier: Programming Language :: Python :: 3.11
Classifier: Programming Language :: Python :: 3.12
Classifier: Topic :: Scientific/Engineering
Classifier: Topic :: Scientific/Engineering :: Mathematics
Classifier: Topic :: Software Development
Classifier: Topic :: Software Development :: Libraries
Classifier: Topic :: Software Development :: Libraries :: Python Modules
Classifier: Topic :: Utilities
Project-URL: Homepage, https://tobydavis.dev/librapid
Project-URL: Documentation, https://librapid.readthedocs.io/en/latest/
Project-URL: Repository, https://github.com/LibRapid/librapid
Project-URL: Download, https://pypi.org/project/librapid/#files
Project-URL: Bug-tracker, https://github.com/LibRapid/librapid/issues
License-File: LICENSE
